[
 {"id": 1, "membernr": 1, "todaysdate": "2020-10-12", "todaysweight": 96.4 },
 {"id": 1, "membernr": 1, "todaysdate": "2020-10-20", "todaysweight": 95.4 },
 {"id": 1, "membernr": 1, "todaysdate": "2020-10-24", "todaysweight": 94.4 },
 {"id": 1, "membernr": 1, "todaysdate": "2020-10-28", "todaysweight": 93.4 },
 {"id": 1, "membernr": 2, "todaysdate": "2020-10-12", "todaysweight": 96.4 },
 {"id": 1, "membernr": 2, "todaysdate": "2020-10-20", "todaysweight": 95.4 },
 {"id": 1, "membernr": 2, "todaysdate": "2020-10-24", "todaysweight": 94.4 },
 {"id": 1, "membernr": 2, "todaysdate": "2020-10-28", "todaysweight": 93.4 },
 {"id": 1, "membernr": 3, "todaysdate": "2020-10-12", "todaysweight": 95.4 },
 {"id": 1, "membernr": 3, "todaysdate": "2020-10-20", "todaysweight": 94.4 },
 {"id": 1, "membernr": 3, "todaysdate": "2020-10-24", "todaysweight": 93.4 },
 {"id": 1, "membernr": 3, "todaysdate": "2020-10-28", "todaysweight": 92.4 },
 {"id": 1, "membernr": 4, "todaysdate": "2020-10-12", "todaysweight": 94.4 },
 {"id": 1, "membernr": 4, "todaysdate": "2020-10-20", "todaysweight": 93.4 },
 {"id": 1, "membernr": 4, "todaysdate": "2020-10-24", "todaysweight": 92.4 },
 {"id": 1, "membernr": 4, "todaysdate": "2020-10-28", "todaysweight": 91.4 },
 {"id": 1, "membernr": 5, "todaysdate": "2020-10-12", "todaysweight": 93.4 },
 {"id": 1, "membernr": 5, "todaysdate": "2020-10-20", "todaysweight": 92.4 },
 {"id": 1, "membernr": 5, "todaysdate": "2020-10-24", "todaysweight": 91.4 },
 {"id": 1, "membernr": 5, "todaysdate": "2020-10-28", "todaysweight": 90.4 },
 {"id": 1, "membernr": 6, "todaysdate": "2020-10-12", "todaysweight": 94.4 },
]
